{
"meta":{"test_sets":[],"test_metrics":[],"learn_metrics":[{"best_value":"Min","name":"RMSE"}],"launch_mode":"Train","parameters":"","iteration_count":100,"learn_sets":["learn"],"name":"experiment"},
"iterations":[
{"learn":[14.04902515],"iteration":0,"passed_time":0.003062648189,"remaining_time":0.3032021707},
{"learn":[13.20277555],"iteration":1,"passed_time":0.003588696194,"remaining_time":0.1758461135},
{"learn":[12.44325007],"iteration":2,"passed_time":0.004064239752,"remaining_time":0.1314104187},
{"learn":[11.73390658],"iteration":3,"passed_time":0.004470840506,"remaining_time":0.1073001721},
{"learn":[11.06616689],"iteration":4,"passed_time":0.004898216873,"remaining_time":0.09306612058},
{"learn":[10.51892195],"iteration":5,"passed_time":0.005350819943,"remaining_time":0.08382951244},
{"learn":[10.06444735],"iteration":6,"passed_time":0.005778234509,"remaining_time":0.07676797276},
{"learn":[9.641791564],"iteration":7,"passed_time":0.006217159766,"remaining_time":0.07149733731},
{"learn":[9.259233732],"iteration":8,"passed_time":0.006662254789,"remaining_time":0.06736279843},
{"learn":[8.867805286],"iteration":9,"passed_time":0.007139028769,"remaining_time":0.06425125893},
{"learn":[8.541878316],"iteration":10,"passed_time":0.007612382413,"remaining_time":0.06159109407},
{"learn":[8.23068324],"iteration":11,"passed_time":0.008588521605,"remaining_time":0.06298249177},
{"learn":[7.995288269],"iteration":12,"passed_time":0.009447732812,"remaining_time":0.06322713497},
{"learn":[7.690141586],"iteration":13,"passed_time":0.01026529104,"remaining_time":0.06305821636},
{"learn":[7.44277432],"iteration":14,"passed_time":0.01075402383,"remaining_time":0.06093946839},
{"learn":[7.237353953],"iteration":15,"passed_time":0.01121281529,"remaining_time":0.05886728026},
{"learn":[7.042411736],"iteration":16,"passed_time":0.01168749373,"remaining_time":0.05706246939},
{"learn":[6.899301849],"iteration":17,"passed_time":0.01214972318,"remaining_time":0.05534873891},
{"learn":[6.750397155],"iteration":18,"passed_time":0.01258203311,"remaining_time":0.05363919378},
{"learn":[6.624954348],"iteration":19,"passed_time":0.01303527563,"remaining_time":0.0521411025},
{"learn":[6.502332572],"iteration":20,"passed_time":0.01348791497,"remaining_time":0.05074025155},
{"learn":[6.406868506],"iteration":21,"passed_time":0.01399811002,"remaining_time":0.04962966278},
{"learn":[6.326186865],"iteration":22,"passed_time":0.01455255949,"remaining_time":0.04871943829},
{"learn":[6.237629164],"iteration":23,"passed_time":0.01504544131,"remaining_time":0.04764389748},
{"learn":[6.16670552],"iteration":24,"passed_time":0.01591367829,"remaining_time":0.04774103487},
{"learn":[6.110096564],"iteration":25,"passed_time":0.01676863069,"remaining_time":0.04772610273},
{"learn":[6.050916593],"iteration":26,"passed_time":0.01762513869,"remaining_time":0.04765315276},
{"learn":[5.989007026],"iteration":27,"passed_time":0.0181081919,"remaining_time":0.04656392203},
{"learn":[5.942206352],"iteration":28,"passed_time":0.0185664951,"remaining_time":0.0454559018},
{"learn":[5.884128492],"iteration":29,"passed_time":0.01902498417,"remaining_time":0.04439162973},
{"learn":[5.849279609],"iteration":30,"passed_time":0.01948747684,"remaining_time":0.04337535168},
{"learn":[5.797033387],"iteration":31,"passed_time":0.01993842736,"remaining_time":0.04236915815},
{"learn":[5.756768179],"iteration":32,"passed_time":0.02047819748,"remaining_time":0.0415769464},
{"learn":[5.733248116],"iteration":33,"passed_time":0.02095032391,"remaining_time":0.04066827583},
{"learn":[5.700046492],"iteration":34,"passed_time":0.02139583496,"remaining_time":0.03973512207},
{"learn":[5.68327707],"iteration":35,"passed_time":0.02176507621,"remaining_time":0.03869346882},
{"learn":[5.660542731],"iteration":36,"passed_time":0.02220233094,"remaining_time":0.0378039689},
{"learn":[5.630366322],"iteration":37,"passed_time":0.02273406656,"remaining_time":0.03709242439},
{"learn":[5.623352945],"iteration":38,"passed_time":0.02329850451,"remaining_time":0.03644125064},
{"learn":[5.595248587],"iteration":39,"passed_time":0.02412836952,"remaining_time":0.03619255428},
{"learn":[5.573345849],"iteration":40,"passed_time":0.02474081705,"remaining_time":0.03560263916},
{"learn":[5.559281302],"iteration":41,"passed_time":0.02519063794,"remaining_time":0.03478707145},
{"learn":[5.543396222],"iteration":42,"passed_time":0.02565272037,"remaining_time":0.03400476886},
{"learn":[5.521086585],"iteration":43,"passed_time":0.02614043525,"remaining_time":0.03326964486},
{"learn":[5.492426449],"iteration":44,"passed_time":0.02656042973,"remaining_time":0.03246274744},
{"learn":[5.477895422],"iteration":45,"passed_time":0.02698861022,"remaining_time":0.03168228156},
{"learn":[5.461239476],"iteration":46,"passed_time":0.02743408082,"remaining_time":0.0309363039},
{"learn":[5.451830879],"iteration":47,"passed_time":0.02786896748,"remaining_time":0.03019138144},
{"learn":[5.438261293],"iteration":48,"passed_time":0.02830183853,"remaining_time":0.02945701562},
{"learn":[5.429554898],"iteration":49,"passed_time":0.02872795944,"remaining_time":0.02872795944},
{"learn":[5.413146688],"iteration":50,"passed_time":0.02916184905,"remaining_time":0.02801824713},
{"learn":[5.403824947],"iteration":51,"passed_time":0.02960543823,"remaining_time":0.02732809682},
{"learn":[5.395350114],"iteration":52,"passed_time":0.03031602227,"remaining_time":0.02688401975},
{"learn":[5.389798674],"iteration":53,"passed_time":0.03110110544,"remaining_time":0.02649353426},
{"learn":[5.378702661],"iteration":54,"passed_time":0.03172454362,"remaining_time":0.02595644478},
{"learn":[5.358608012],"iteration":55,"passed_time":0.03225599707,"remaining_time":0.0253439977},
{"learn":[5.348834509],"iteration":56,"passed_time":0.0326892238,"remaining_time":0.02466029164},
{"learn":[5.344278385],"iteration":57,"passed_time":0.03311556652,"remaining_time":0.02398023783},
{"learn":[5.332299589],"iteration":58,"passed_time":0.03352502681,"remaining_time":0.02329705253},
{"learn":[5.324024877],"iteration":59,"passed_time":0.03394783653,"remaining_time":0.02263189102},
{"learn":[5.310232763],"iteration":60,"passed_time":0.03436486425,"remaining_time":0.02197097878},
{"learn":[5.302820736],"iteration":61,"passed_time":0.03479000319,"remaining_time":0.02132290518},
{"learn":[5.294739854],"iteration":62,"passed_time":0.03523938527,"remaining_time":0.02069614691},
{"learn":[5.288924148],"iteration":63,"passed_time":0.03576831432,"remaining_time":0.02011967681},
{"learn":[5.279799584],"iteration":64,"passed_time":0.03629759648,"remaining_time":0.01954485964},
{"learn":[5.274360819],"iteration":65,"passed_time":0.03678191703,"remaining_time":0.01894826029},
{"learn":[5.267507465],"iteration":66,"passed_time":0.03748148377,"remaining_time":0.01846102932},
{"learn":[5.264191227],"iteration":67,"passed_time":0.0382875695,"remaining_time":0.01801767976},
{"learn":[5.255940638],"iteration":68,"passed_time":0.03898813779,"remaining_time":0.01751640973},
{"learn":[5.24998685],"iteration":69,"passed_time":0.0395569822,"remaining_time":0.01695299237},
{"learn":[5.244627233],"iteration":70,"passed_time":0.04003866728,"remaining_time":0.01635382185},
{"learn":[5.239558898],"iteration":71,"passed_time":0.04052312105,"remaining_time":0.01575899152},
{"learn":[5.235264554],"iteration":72,"passed_time":0.0409460919,"remaining_time":0.01514444495},
{"learn":[5.231617027],"iteration":73,"passed_time":0.04137664111,"remaining_time":0.01453773877},
{"learn":[5.22660688],"iteration":74,"passed_time":0.04180015543,"remaining_time":0.01393338514},
{"learn":[5.21798742],"iteration":75,"passed_time":0.04223281141,"remaining_time":0.01333667729},
{"learn":[5.213847377],"iteration":76,"passed_time":0.04265560539,"remaining_time":0.01274128473},
{"learn":[5.202746865],"iteration":77,"passed_time":0.04309384016,"remaining_time":0.01215467287},
{"learn":[5.194754311],"iteration":78,"passed_time":0.04353445874,"remaining_time":0.01157245106},
{"learn":[5.188945348],"iteration":79,"passed_time":0.04395816278,"remaining_time":0.01098954069},
{"learn":[5.181628538],"iteration":80,"passed_time":0.04440313485,"remaining_time":0.01041555015},
{"learn":[5.177831225],"iteration":81,"passed_time":0.04522854589,"remaining_time":0.009928217389},
{"learn":[5.172737434],"iteration":82,"passed_time":0.04602498373,"remaining_time":0.009426803897},
{"learn":[5.161252111],"iteration":83,"passed_time":0.04693571955,"remaining_time":0.008940137057},
{"learn":[5.158693812],"iteration":84,"passed_time":0.04747400822,"remaining_time":0.008377766156},
{"learn":[5.14844995],"iteration":85,"passed_time":0.04794773199,"remaining_time":0.007805444742},
{"learn":[5.144310718],"iteration":86,"passed_time":0.04854042053,"remaining_time":0.007253166286},
{"learn":[5.139012291],"iteration":87,"passed_time":0.04898468671,"remaining_time":0.006679730006},
{"learn":[5.129852617],"iteration":88,"passed_time":0.049442241,"remaining_time":0.006110838775},
{"learn":[5.125669689],"iteration":89,"passed_time":0.04986761203,"remaining_time":0.005540845781},
{"learn":[5.122378658],"iteration":90,"passed_time":0.05030409795,"remaining_time":0.004975130567},
{"learn":[5.117214953],"iteration":91,"passed_time":0.05072191247,"remaining_time":0.004410601084},
{"learn":[5.11235693],"iteration":92,"passed_time":0.05115336435,"remaining_time":0.00385025323},
{"learn":[5.107334439],"iteration":93,"passed_time":0.05158556,"remaining_time":0.003292695319},
{"learn":[5.104405965],"iteration":94,"passed_time":0.05245649537,"remaining_time":0.002760868177},
{"learn":[5.100373809],"iteration":95,"passed_time":0.05317969982,"remaining_time":0.002215820826},
{"learn":[5.091849696],"iteration":96,"passed_time":0.05376862359,"remaining_time":0.001662947121},
{"learn":[5.087554598],"iteration":97,"passed_time":0.05430800465,"remaining_time":0.001108326625},
{"learn":[5.081739613],"iteration":98,"passed_time":0.05479709794,"remaining_time":0.0005535060398},
{"learn":[5.077942791],"iteration":99,"passed_time":0.05527966514,"remaining_time":0}
]}